NibblerFinal/flags_module.v
module flags_module(input clk,enable,reset,C,Zeta, output C_out,Z_out); // instanciar modulo

  wire clk,enable,reset,C,Zeta;     // instanciar variables a utilizar y asignar valores
  reg C_out=0;
  reg Z_out=0;

  always @ (posedge clk)
    begin
      if(reset) 
        begin         //si recibe reset reinicia las variables Z y C
          C_out <= 0;
          Z_out <= 0;
        end
      else if (enable==1) 
        begin       // si esta habilitado almacena los datos de las banderas
          C_out <=  C;
          Z_out <=  Zeta;
        end
    end

endmodule

NibblerFinal/accumulator.v
module accumulator(input clk,enable,reset, input [3:0]A_in, output [3:0]A_out); //instanciar el modulo

  wire clk,enable,reset;        // instanciar variables internas, entrada y salidas.
  wire [3:0]A_in;
  reg [3:0]A_out=0;

  always @ (posedge clk)        //funciona cada vez que recibe clk o reset
    begin
      if(reset)                // si es reset reiniciara todo el contador
        begin
          A_out <= 0;
        end
      else if (enable==1)     // si esta habilitado
        begin                   // cambia el valor del contador si esta habilitado, de lo contrario mantiene el mismo valor
          A_out <= A_in;
        end
    end

endmodule

NibblerFinal/buffer.v
module buffer(input enable, input [3:0]in, output [3:0]out);   //instanciar modulo

  wire enable;                // instanciar variables a usar
  wire [3:0]in;
  reg [3:0]out;

  always @ (*) 
  begin                       //mientras este habilitado,
    if (enable) 
      begin
        out[3:0] <= in[3:0];   // almacenara algo nuevo que entre al buffer y lo guardara
      end
    else 
      begin
        out[3:0] <= 4'bzzzz;   // de lo contrario lo tendra en alta impedancia
      end
  end

endmodule

NibblerFinal/rom.v
module rom(input wire [11:0] address, output wire [7:0] dat); //instanciar modulo

  reg [7:0] rom [0:4095];     // estableceer variables a utilizar y asignar datos
  assign dat = rom[address];

  initial begin                       // aca abre el prog_rom.list que son las instrucciones y las envia
    $readmemh("memory.list", rom);  // al decoder a travez de dat luego de leer el address
  end

endmodule

NibblerFinal/ram.v
module ram(input [11:0]address, input weRam,csRam, inout [3:0]salida); // instancia modulo

    wire [11:0]address;     //asigna variables que se utilizaran
    wire weRam,csRam;
    reg [3:0] ram [0:4095];
    reg [3:0] data_out;

    assign salida = (csRam&&!weRam) ? data_out : 4'bzzzz;

    always @ (address or salida or csRam or weRam) //Csram se encarga de activar la ram o desactivarla, si esta en 0 esta en alta impedancia
    begin                                          //Weram se encarga de habilitarlo como si fuera lectura o escritura, 1 para escritura y 0 para lectura
      if ((csRam==1) && (weRam==1))               // salida es el puerto bidireccional de la ram
        begin
          ram[address]<=salida;
        end
      else if ((csRam==1)&&(weRam==0)) 
        begin
          data_out<=ram[address];
        end
    end


endmodule

NibblerFinal/program_counter.v
module program_counter(input clk,enable,reset,load, input [11:0]in, output [11:0]C); //instanciar modulo

  wire clk,enable,reset,load; // declarar variables a usar y asignar datos
  wire [11:0]in;
  reg [11:0]C=0;

  always @ (posedge clk)    // ejecutar al clk
    begin
      if (load) 
        begin     // en caso se quiera cargar un valor 
          C <= in;
        end
      else if(reset) 
        begin    //en caso que halla reset restablece
          C <= 0;
        end
      else if (enable) 
        begin    // si esta habilitado ira sumando al contador 
          C <= C+1;
        end
    end

endmodule

NibblerFinal/alu.v
module alu(input [2:0]S, input [3:0]A,B, output C,Zeta, output [3:0]Y_out);     //instanciar modulo

  wire [2:0]S;                      // instanciar variables internas, entrada y salidas.
  wire [3:0]A,B;
  reg [3:0]Y_out;
  reg C=0;
  reg Zeta=0;

  always @ (*)            //casos del selector 
    begin                 // caso que reciba 000 dara como salida A
      if(S==0) 
        begin            
          Y_out<=A;
          C<=0;
          Zeta= (Y_out == 0);
        end
      else if (S==2) 
        begin                // en caso que reciba 001 dara B como salida
          Y_out<=B;
          C<=0;
          Zeta= (Y_out == 0);
        end
      else if (S==3) 
        begin               // en caso reciba 010 sumara A y B
          Y_out<=(A+B);
          Zeta= (Y_out == 0);
              if((A+B)>15)    //Agregara 1 al carry si hay overflow en la suma
              begin
                C<=1;
              end
            else          // de lo contrario mantiene el carry en 0
              begin
                C<=0;
              end
        end
      else if (S==1) 
        begin             // en caso de recibir 011 comparara entre A y B
          Y_out<=(A-B);
          if (A==B) 
            begin
              Zeta = (Y_out == 0);        // si A y B son iguales Carry = 0, si A es mayor C = 0 de lo contrario devolvera 1 
              C<=0;
            end
          else if (A>B) 
            begin
              Zeta= (Y_out == 0);
              C<=0;
            end
          else 
            begin
              C<=1;
              Zeta= (Y_out == 0);
            end
        end
      else if (S==4)          //en caso de recibir 100 hara un NAND entre A y B
        begin
          Y_out<=(~(A&B));    
          C<=0;
          Zeta= (Y_out == 0);
        end
      else 
        begin
          Y_out<=Y_out;     // de lo contrario de recibir algo mas en el selector devolvera Y 
          C<=0;
          Zeta= (Y_out == 0);
        end
    end

endmodule

NibblerFinal/fetch.v
module fetch(input clk,enable,reset, input [7:0]D_in, output [7:0]D_out); //instanciar modulo

  wire clk,enable,reset; // instanciar variables a utilizar
  wire [7:0]D_in;
  reg [7:0]D_out=0;

  always @ (posedge clk or posedge reset)
    begin
      if(reset) 
        begin           // si recibe reset reinicia el fetch
          D_out <= 0;
        end
      else if (enable) 
        begin    //de lo contrario al recibir el enable devuelve la data
          D_out <= D_in;
        end
    end

endmodule

NibblerFinal/decoder.v
module decoder(input phase,C,Zeta, input [3:0]i, output [12:0]out); //instanciar modulo

  wire phase,C,Zeta;        //instanciar variables a utilizar y asignar valores de salida
  wire [3:0]i;
  reg [12:0]carry=0;
  assign out = carry;     

  always @ (phase or C or Zeta or i)  //inician las instrucciones
  begin    
    if (phase==0) 
      begin                               //ANY
        carry  = 13'b1000000001000;          
      end
    else 
      begin
        if (i==4'b0000 && C==1) 
          begin
            carry  <= 13'b0100000001000;    //JC CARRY 1
          end
        else if (i==4'b0000 && C==0) 
          begin
            carry  = 13'b1000000001000;     //JC CARRY 0
          end
        else if (i==4'b0001 && C==1) 
          begin
            carry  = 13'b1000000001000;     //JNC  CARRY 1
          end
        else if (i==4'b0001 && C==0) 
          begin
            carry  = 13'b0100000001000;     //JNC  CARRY 0
          end
        else if (i==4'b0010) 
          begin
            carry  = 13'b0001001000010;     // CMPI
          end
        else if (i==4'b0011) 
          begin
            carry  = 13'b1001001100000;   // CMPM
          end
        else if (i==4'b0100) 
          begin
            carry  = 13'b0011010000010;   // LIT
          end
        else if (i==4'b0101) 
          begin
            carry  = 13'b0011010000100;   // IN
          end
        else if (i==4'b0110) 
          begin
            carry  = 13'b1011010100000;   // LD
          end
        else if (i==4'b0111) 
          begin
            carry  = 13'b1000000111000;   //ST
          end
        else if (i==4'b1000 && Zeta==1) 
          begin
            carry  = 13'b0100000001000;   //JZ Z=1
          end
        else if (i==4'b1000 && Zeta==0) 
          begin
            carry  = 13'b1000000001000;   //JZ Z=0
          end
        else if (i==4'b1001 && Zeta==1) 
          begin
            carry  = 13'b1000000001000;   // JNZ Z=1
          end
        else if (i==4'b1001 && Zeta==0) 
          begin
            carry  = 13'b0100000001000;   // JNZ Z=0
          end
        else if (i==4'b1010) 
          begin
            carry  = 13'b0011011000010;   // ADDI
          end
        else if (i==4'b1011) 
          begin
            carry  = 13'b1011011100000;   // ADDM
          end
        else if (i==4'b1100) 
          begin
            carry  = 13'b0100000001000;   // JMP
          end
        else if (i==4'b1101) 
          begin
            carry  = 13'b0000000001001;   //OUT
          end
        else if (i==4'b1110) 
          begin
            carry  = 13'b0011100000010;   //NANDI
          end
        else if (i==4'b1111) 
          begin
            carry  = 13'b1011100100000;   //NANDM
          end
      end
  end

endmodule

NibblerFinal/phase_module.v
module phase_module(input clk,reset, output out); //instanciar modulo

reg out = 0;      //establece variables a usar y asigna valores

always @ (posedge clk)
  begin
    out <= ~out;      //niega y asigna out
  end

endmodule

NibblerFinal/uP.v
module uP(
  input clock,reset, 
  input [3:0]pushbuttons, 
  output phase,c_flag,z_flag, 
  output [3:0] instr,oprnd,data_bus,FF_out,accu, 
  output [7:0] program_byte, 
  output [11:0] PC, address_RAM);

  wire [12:0]d_out;
  wire incPC,loadPC,loadA,loadFlags,csRAM,weRAM,oeALU,oeIN,oeOprnd,loadOut,C,Zeta;
  wire [2:0]S;
  wire [3:0]ALU_out;
  wire [7:0]fetch_out;
  assign address_RAM[11:8] = oprnd;
  assign address_RAM[7:0] = program_byte;
  assign instr = fetch_out[7:4];
  assign oprnd = fetch_out[3:0];
  assign incPC = d_out[12];
  assign loadPC = d_out[11];
  assign loadA = d_out[10];
  assign loadFlags = d_out[9];
  assign S = d_out[8:6];
  assign csRAM = d_out[5];
  assign weRAM = d_out[4];
  assign oeALU = d_out[3];
  assign oeIN = d_out[2];
  assign oeOprnd = d_out[1];
  assign loadOut = d_out[0];

  phase_module     phase_module (clock,reset,phase);
  decoder          decoder (phase,c_flag,z_flag,instr,d_out);
  fetch            fetch  (clock,~phase,reset,program_byte,fetch_out);
  accumulator      accumulator (clock,loadA,reset,ALU_out,accu);
  alu              alu (S,accu,data_bus,C,Zeta,ALU_out);
  program_counter  program_counter (clock,incPC,reset,loadPC,address_RAM,PC);
  ram              ram (address_RAM,weRAM,csRAM,data_bus);
  rom              rom (PC,program_byte);
  buffer           buffer_alu (oeALU,ALU_out,data_bus);
  buffer           buffer_fetch (oeOprnd,oprnd,data_bus);
  buffer           buffer_in (oeIN,pushbuttons,data_bus);
  accumulator      ffout (clock,loadOut,reset,data_bus,FF_out);
  flags_module     flags_module (clock,loadFlags,reset,C,Zeta,c_flag,z_flag);

endmodule

Testbench propio/uP_tb.v
module testbench();

    reg clock, reset;
    reg [3:0] pushbuttons;
    wire phase, c_flag, z_flag;
    wire [3:0] instr, oprnd, accu, data_bus, FF_out;
    wire [7:0] program_byte;
    wire [11:0] PC, address_RAM;


    uP uPmodule(.clock(clock),
                .reset(reset),
                .pushbuttons(pushbuttons),
                .phase(phase),
                .c_flag(c_flag),
                .z_flag(z_flag),
                .instr(instr),
                .oprnd(oprnd),
                .accu(accu),
                .data_bus(data_bus),
                .FF_out(FF_out),
                .program_byte(program_byte),
                .PC(PC),
                .address_RAM(address_RAM));

    initial
        #650 $finish;

    always
        #5 clock = ~clock;

    initial 
    begin
        clock = 0; reset = 1; pushbuttons = 4'b1100; // Dec 12, Hex C
        #2 reset = 0;
    end

    initial 
    begin
        $dumpfile("uP_tb.vcd");
        $dumpvars(0, testbench);
    end


endmodule

Testbench propio/uP_tb.vcd
$date
	Sat Nov 21 10:22:05 2020
$end
$version
	Icarus Verilog
$end
$timescale
	1ps
$end
$scope module testbench $end
$var wire 4 ! data_bus [3:0] $end
$var wire 1 " z_flag $end
$var wire 8 # program_byte [7:0] $end
$var wire 1 $ phase $end
$var wire 4 % oprnd [3:0] $end
$var wire 4 & instr [3:0] $end
$var wire 1 ' c_flag $end
$var wire 12 ( address_RAM [11:0] $end
$var wire 4 ) accu [3:0] $end
$var wire 12 * PC [11:0] $end
$var wire 4 + FF_out [3:0] $end
$var reg 1 , clock $end
$var reg 4 - pushbuttons [3:0] $end
$var reg 1 . reset $end
$scope module uPmodule $end
$var wire 1 , clock $end
$var wire 4 / data_bus [3:0] $end
$var wire 4 0 pushbuttons [3:0] $end
$var wire 1 . reset $end
$var wire 1 " z_flag $end
$var wire 1 1 weRAM $end
$var wire 8 2 program_byte [7:0] $end
$var wire 1 $ phase $end
$var wire 4 3 oprnd [3:0] $end
$var wire 1 4 oeOprnd $end
$var wire 1 5 oeIN $end
$var wire 1 6 oeALU $end
$var wire 1 7 loadPC $end
$var wire 1 8 loadOut $end
$var wire 1 9 loadFlags $end
$var wire 1 : loadA $end
$var wire 4 ; instr [3:0] $end
$var wire 1 < incPC $end
$var wire 8 = fetch_out [7:0] $end
$var wire 13 > d_out [12:0] $end
$var wire 1 ? csRAM $end
$var wire 1 ' c_flag $end
$var wire 12 @ address_RAM [11:0] $end
$var wire 4 A accu [3:0] $end
$var wire 1 B Zeta $end
$var wire 3 C S [2:0] $end
$var wire 12 D PC [11:0] $end
$var wire 4 E FF_out [3:0] $end
$var wire 1 F C $end
$var wire 4 G ALU_out [3:0] $end
$scope module accumulator $end
$var wire 1 , clk $end
$var wire 1 : enable $end
$var wire 1 . reset $end
$var wire 4 H A_in [3:0] $end
$var reg 4 I A_out [3:0] $end
$upscope $end
$scope module alu $end
$var wire 4 J A [3:0] $end
$var wire 4 K B [3:0] $end
$var wire 3 L S [2:0] $end
$var reg 1 F C $end
$var reg 4 M Y_out [3:0] $end
$var reg 1 B Zeta $end
$upscope $end
$scope module buffer_alu $end
$var wire 1 6 enable $end
$var wire 4 N in [3:0] $end
$var reg 4 O out [3:0] $end
$upscope $end
$scope module buffer_fetch $end
$var wire 1 4 enable $end
$var wire 4 P in [3:0] $end
$var reg 4 Q out [3:0] $end
$upscope $end
$scope module buffer_in $end
$var wire 1 5 enable $end
$var wire 4 R in [3:0] $end
$var reg 4 S out [3:0] $end
$upscope $end
$scope module decoder $end
$var wire 4 T i [3:0] $end
$var wire 13 U out [12:0] $end
$var wire 1 $ phase $end
$var wire 1 " Zeta $end
$var wire 1 ' C $end
$var reg 13 V carry [12:0] $end
$upscope $end
$scope module fetch $end
$var wire 1 , clk $end
$var wire 1 W enable $end
$var wire 1 . reset $end
$var wire 8 X D_in [7:0] $end
$var reg 8 Y D_out [7:0] $end
$upscope $end
$scope module ffout $end
$var wire 4 Z A_in [3:0] $end
$var wire 1 , clk $end
$var wire 1 8 enable $end
$var wire 1 . reset $end
$var reg 4 [ A_out [3:0] $end
$upscope $end
$scope module flags_module $end
$var wire 1 F C $end
$var wire 1 B Zeta $end
$var wire 1 , clk $end
$var wire 1 9 enable $end
$var wire 1 . reset $end
$var reg 1 ' C_out $end
$var reg 1 " Z_out $end
$upscope $end
$scope module phase_module $end
$var wire 1 , clk $end
$var wire 1 . reset $end
$var reg 1 $ out $end
$upscope $end
$scope module program_counter $end
$var wire 1 , clk $end
$var wire 1 < enable $end
$var wire 12 \ in [11:0] $end
$var wire 1 7 load $end
$var wire 1 . reset $end
$var reg 12 ] C [11:0] $end
$upscope $end
$scope module ram $end
$var wire 12 ^ address [11:0] $end
$var wire 1 ? csRam $end
$var wire 4 _ salida [3:0] $end
$var wire 1 1 weRam $end
$var reg 4 ` data_out [3:0] $end
$upscope $end
$scope module rom $end
$var wire 12 a address [11:0] $end
$var wire 8 b dat [7:0] $end
$upscope $end
$upscope $end
$upscope $end
$enddefinitions $end
#0
$dumpvars
b1010000 b
b0 a
bx `
b0 _
b1010000 ^
b0 ]
b1010000 \
b0 [
b0 Z
b0 Y
b1010000 X
1W
b1000000001000 V
b1000000001000 U
b0 T
bz S
b1100 R
bz Q
b0 P
b0 O
b0 N
b0 M
b0 L
b0 K
b0 J
b0 I
b0 H
b0 G
0F
b0 E
b0 D
b0 C
1B
b0 A
b1010000 @
0?
b1000000001000 >
b0 =
1<
b0 ;
0:
09
08
07
16
05
04
b0 3
b1010000 2
01
b1100 0
b0 /
1.
b1100 -
0,
b0 +
b0 *
b0 )
b1010000 (
0'
b0 &
b0 %
0$
b1010000 #
0"
b0 !
$end
#2
0.
#5
0B
b1100 G
b1100 H
b1100 M
b1100 N
b1100 S
b1100 !
b1100 /
b1100 K
b1100 Z
b1100 _
bz O
15
06
b10 C
b10 L
19
1:
0<
0W
b11010000100 >
b11010000100 U
b11010000100 V
b101 &
b101 ;
b101 T
1$
b11010000 (
b11010000 @
b11010000 \
b11010000 ^
b11010000 #
b11010000 2
b11010000 X
b11010000 b
b1 *
b1 D
b1 ]
b1 a
b1010000 =
b1010000 Y
1,
#10
0,
#15
bz S
b1100 O
05
16
b0 C
b0 L
09
0:
1<
1W
b1000000001000 >
b1000000001000 U
b1000000001000 V
b1100 )
b1100 A
b1100 I
b1100 J
0$
1,
#20
0,
#25
18
0<
0W
b1001 >
b1001 U
b1001 V
b1101 &
b1101 ;
b1101 T
1$
b1001010 (
b1001010 @
b1001010 \
b1001010 ^
b1001010 #
b1001010 2
b1001010 X
b1001010 b
b10 *
b10 D
b10 ]
b10 a
b11010000 =
b11010000 Y
1,
#30
0,
#35
08
1<
1W
b1000000001000 >
b1000000001000 U
b1000000001000 V
b1100 +
b1100 E
b1100 [
0$
1,
#40
0,
#45
b1010 G
b1010 H
b1010 M
b1010 N
b1010 Q
b1010 !
b1010 /
b1010 K
b1010 Z
b1010 _
bz O
14
06
b10 C
b10 L
19
1:
0<
0W
b11010000010 >
b11010000010 U
b11010000010 V
b1010 %
b1010 3
b1010 P
b100 &
b100 ;
b100 T
1$
b101010101000 (
b101010101000 @
b101010101000 \
b101010101000 ^
b10101000 #
b10101000 2
b10101000 X
b10101000 b
b11 *
b11 D
b11 ]
b11 a
b1001010 =
b1001010 Y
1,
#50
0,
#55
bz Q
b1010 O
04
16
b0 C
b0 L
09
0:
1<
1W
b1000000001000 >
b1000000001000 U
b1000000001000 V
b1010 )
b1010 A
b1010 I
b1010 J
0$
1,
#60
0,
#65
b1000 Q
b1000 !
b1000 /
b1000 K
b1000 Z
b1000 _
bz O
1F
b10 G
b10 H
b10 M
b10 N
14
06
b11 C
b11 L
19
1:
0<
0W
b11011000010 >
b11011000010 U
b11011000010 V
b1000 %
b1000 3
b1000 P
b1010 &
b1010 ;
b1010 T
1$
b100001000000 (
b100001000000 @
b100001000000 \
b100001000000 ^
b1000000 #
b1000000 2
b1000000 X
b1000000 b
b100 *
b100 D
b100 ]
b100 a
b10101000 =
b10101000 Y
1,
#70
0,
#75
bz Q
b10 !
b10 /
b10 K
b10 Z
b10 _
b10 O
0F
b10 G
b10 H
b10 M
b10 N
04
16
b0 C
b0 L
09
0:
1<
1W
b1000000001000 >
b1000000001000 U
b1000000001000 V
1'
b10 )
b10 A
b10 I
b10 J
0$
1,
#80
0,
#85
1B
b0 G
b0 H
b0 M
b0 N
b0 Q
b0 !
b0 /
b0 K
b0 Z
b0 _
bz O
14
06
b10 C
b10 L
19
1:
0<
0W
b11010000010 >
b11010000010 U
b11010000010 V
b0 %
b0 3
b0 P
b100 &
b100 ;
b100 T
1$
b10100101 (
b10100101 @
b10100101 \
b10100101 ^
b10100101 #
b10100101 2
b10100101 X
b10100101 b
b101 *
b101 D
b101 ]
b101 a
b1000000 =
b1000000 Y
1,
#90
0,
#95
bz Q
b0 O
04
16
b0 C
b0 L
09
0:
1<
1W
b1000000001000 >
b1000000001000 U
b1000000001000 V
1"
0'
b0 )
b0 A
b0 I
b0 J
0$
1,
#100
0,
#105
0B
b101 G
b101 H
b101 M
b101 N
b101 Q
b101 !
b101 /
b101 K
b101 Z
b101 _
bz O
14
06
b11 C
b11 L
19
1:
0<
0W
b11011000010 >
b11011000010 U
b11011000010 V
b101 %
b101 3
b101 P
b1010 &
b1010 ;
b1010 T
1$
b10100101010 (
b10100101010 @
b10100101010 \
b10100101010 ^
b101010 #
b101010 2
b101010 X
b101010 b
b110 *
b110 D
b110 ]
b110 a
b10100101 =
b10100101 Y
1,
#110
0,
#115
bz Q
b101 O
b101 G
b101 H
b101 M
b101 N
04
16
b0 C
b0 L
09
0:
1<
1W
b1000000001000 >
b1000000001000 U
b1000000001000 V
0"
b101 )
b101 A
b101 I
b101 J
0$
1,
#120
0,
#125
1F
0B
b1010 Q
b1010 !
b1010 /
b1010 K
b1010 Z
b1010 _
bz O
b1011 G
b1011 H
b1011 M
b1011 N
14
06
b1 C
b1 L
19
0<
0W
b1001000010 >
b1001000010 U
b1001000010 V
b1010 %
b1010 3
b1010 P
b10 &
b10 ;
b10 T
1$
b101011101011 (
b101011101011 @
b101011101011 \
b101011101011 ^
b11101011 #
b11101011 2
b11101011 X
b11101011 b
b111 *
b111 D
b111 ]
b111 a
b101010 =
b101010 Y
1,
#130
0,
#135
bz Q
b101 !
b101 /
b101 K
b101 Z
b101 _
b101 O
0F
b101 G
b101 H
b101 M
b101 N
04
16
b0 C
b0 L
09
1<
1W
b1000000001000 >
b1000000001000 U
b1000000001000 V
1'
0$
1,
#140
0,
#145
b1011 Q
b1011 !
b1011 /
b1011 K
b1011 Z
b1011 _
bz O
b1110 G
b1110 H
b1110 M
b1110 N
14
06
b100 C
b100 L
19
1:
0<
0W
b11100000010 >
b11100000010 U
b11100000010 V
b1011 %
b1011 3
b1011 P
b1110 &
b1110 ;
b1110 T
1$
b101100010000 (
b101100010000 @
b101100010000 \
b101100010000 ^
b10000 #
b10000 2
b10000 X
b10000 b
b1000 *
b1000 D
b1000 ]
b1000 a
b11101011 =
b11101011 Y
1,
#150
0,
#155
bz Q
b1110 !
b1110 /
b1110 K
b1110 Z
b1110 _
b1110 O
b1110 G
b1110 H
b1110 M
b1110 N
04
16
b0 C
b0 L
09
0:
1<
1W
b1000000001000 >
b1000000001000 U
b1000000001000 V
0'
b1110 )
b1110 A
b1110 I
b1110 J
0$
1,
#160
0,
#165
17
0<
0W
b100000001000 >
b100000001000 U
b100000001000 V
b0 %
b0 3
b0 P
b1 &
b1 ;
b1 T
1$
b1100 (
b1100 @
b1100 \
b1100 ^
b1100 #
b1100 2
b1100 X
b1100 b
b1001 *
b1001 D
b1001 ]
b1001 a
b10000 =
b10000 Y
1,
#170
0,
#175
07
1<
1W
b1000000001000 >
b1000000001000 U
b1000000001000 V
b1001111 (
b1001111 @
b1001111 \
b1001111 ^
b1001111 #
b1001111 2
b1001111 X
b1001111 b
b1100 *
b1100 D
b1100 ]
b1100 a
0$
1,
#180
0,
#185
b1111 G
b1111 H
b1111 M
b1111 N
b1111 Q
b1111 !
b1111 /
b1111 K
b1111 Z
b1111 _
bz O
14
06
b10 C
b10 L
19
1:
0<
0W
b11010000010 >
b11010000010 U
b11010000010 V
b1111 %
b1111 3
b1111 P
b100 &
b100 ;
b100 T
1$
b111110100001 (
b111110100001 @
b111110100001 \
b111110100001 ^
b10100001 #
b10100001 2
b10100001 X
b10100001 b
b1101 *
b1101 D
b1101 ]
b1101 a
b1001111 =
b1001111 Y
1,
#190
0,
#195
bz Q
b1111 O
04
16
b0 C
b0 L
09
0:
1<
1W
b1000000001000 >
b1000000001000 U
b1000000001000 V
b1111 )
b1111 A
b1111 I
b1111 J
0$
1,
#200
0,
#205
1B
b1 Q
b1 !
b1 /
b1 K
b1 Z
b1 _
bz O
1F
b0 G
b0 H
b0 M
b0 N
14
06
b11 C
b11 L
19
1:
0<
0W
b11011000010 >
b11011000010 U
b11011000010 V
b1 %
b1 3
b1 P
b1010 &
b1010 ;
b1010 T
1$
b100000000 (
b100000000 @
b100000000 \
b100000000 ^
b0 #
b0 2
b0 X
b0 b
b1110 *
b1110 D
b1110 ]
b1110 a
b10100001 =
b10100001 Y
1,
#210
0,
#215
bz Q
b0 !
b0 /
b0 K
b0 Z
b0 _
b0 O
0F
b0 G
b0 H
b0 M
b0 N
04
16
b0 C
b0 L
09
0:
1<
1W
b1000000001000 >
b1000000001000 U
b1000000001000 V
1"
1'
b0 )
b0 A
b0 I
b0 J
0$
1,
#220
0,
#225
17
0<
b100000001000 >
b100000001000 U
b100000001000 V
0W
b0 %
b0 3
b0 P
b0 &
b0 ;
b0 T
1$
b10010 (
b10010 @
b10010 \
b10010 ^
b10010 #
b10010 2
b10010 X
b10010 b
b1111 *
b1111 D
b1111 ]
b1111 a
b0 =
b0 Y
1,
#230
0,
#235
07
1<
1W
b1000000001000 >
b1000000001000 U
b1000000001000 V
b1001111 (
b1001111 @
b1001111 \
b1001111 ^
b1001111 #
b1001111 2
b1001111 X
b1001111 b
b10010 *
b10010 D
b10010 ]
b10010 a
0$
1,
#240
0,
#245
0B
b1111 G
b1111 H
b1111 M
b1111 N
b1111 Q
b1111 !
b1111 /
b1111 K
b1111 Z
b1111 _
bz O
14
06
b10 C
b10 L
19
1:
0<
0W
b11010000010 >
b11010000010 U
b11010000010 V
b1111 %
b1111 3
b1111 P
b100 &
b100 ;
b100 T
1$
b111101000000 (
b111101000000 @
b111101000000 \
b111101000000 ^
b1000000 #
b1000000 2
b1000000 X
b1000000 b
b10011 *
b10011 D
b10011 ]
b10011 a
b1001111 =
b1001111 Y
1,
#250
0,
#255
bz Q
b1111 O
04
16
b0 C
b0 L
09
0:
1<
1W
b1000000001000 >
b1000000001000 U
b1000000001000 V
0"
0'
b1111 )
b1111 A
b1111 I
b1111 J
0$
1,
#260
0,
#265
1B
b0 G
b0 H
b0 M
b0 N
b0 Q
b0 !
b0 /
b0 K
b0 Z
b0 _
bz O
14
06
b10 C
b10 L
19
1:
0<
0W
b11010000010 >
b11010000010 U
b11010000010 V
b0 %
b0 3
b0 P
1$
b10000000 (
b10000000 @
b10000000 \
b10000000 ^
b10000000 #
b10000000 2
b10000000 X
b10000000 b
b10100 *
b10100 D
b10100 ]
b10100 a
b1000000 =
b1000000 Y
1,
#270
0,
#275
bz Q
b0 O
04
16
b0 C
b0 L
09
0:
1<
1W
b1000000001000 >
b1000000001000 U
b1000000001000 V
1"
b0 )
b0 A
b0 I
b0 J
0$
1,
#280
0,
#285
17
0<
0W
b100000001000 >
b100000001000 U
b100000001000 V
b1000 &
b1000 ;
b1000 T
1$
b10111 (
b10111 @
b10111 \
b10111 ^
b10111 #
b10111 2
b10111 X
b10111 b
b10101 *
b10101 D
b10101 ]
b10101 a
b10000000 =
b10000000 Y
1,
#290
0,
#295
07
1<
1W
b1000000001000 >
b1000000001000 U
b1000000001000 V
b1001100 (
b1001100 @
b1001100 \
b1001100 ^
b1001100 #
b1001100 2
b1001100 X
b1001100 b
b10111 *
b10111 D
b10111 ]
b10111 a
0$
1,
#300
0,
#305
0B
b1100 G
b1100 H
b1100 M
b1100 N
b1100 Q
b1100 !
b1100 /
b1100 K
b1100 Z
b1100 _
bz O
14
06
b10 C
b10 L
19
1:
0<
0W
b11010000010 >
b11010000010 U
b11010000010 V
b1100 %
b1100 3
b1100 P
b100 &
b100 ;
b100 T
1$
b110010010000 (
b110010010000 @
b110010010000 \
b110010010000 ^
b10010000 #
b10010000 2
b10010000 X
b10010000 b
b11000 *
b11000 D
b11000 ]
b11000 a
b1001100 =
b1001100 Y
1,
#310
0,
#315
bz Q
b1100 O
04
16
b0 C
b0 L
09
0:
1<
1W
b1000000001000 >
b1000000001000 U
b1000000001000 V
0"
b1100 )
b1100 A
b1100 I
b1100 J
0$
1,
#320
0,
#325
17
0<
0W
b100000001000 >
b100000001000 U
b100000001000 V
b0 %
b0 3
b0 P
b1001 &
b1001 ;
b1001 T
1$
b11110 (
b11110 @
b11110 \
b11110 ^
b11110 #
b11110 2
b11110 X
b11110 b
b11001 *
b11001 D
b11001 ]
b11001 a
b10010000 =
b10010000 Y
1,
#330
0,
#335
07
1<
1W
b1000000001000 >
b1000000001000 U
b1000000001000 V
b1001011 (
b1001011 @
b1001011 \
b1001011 ^
b1001011 #
b1001011 2
b1001011 X
b1001011 b
b11110 *
b11110 D
b11110 ]
b11110 a
0$
1,
#340
0,
#345
b1011 G
b1011 H
b1011 M
b1011 N
b1011 Q
b1011 !
b1011 /
b1011 K
b1011 Z
b1011 _
bz O
14
06
b10 C
b10 L
19
1:
0<
0W
b11010000010 >
b11010000010 U
b11010000010 V
b1011 %
b1011 3
b1011 P
b100 &
b100 ;
b100 T
1$
b101111000000 (
b101111000000 @
b101111000000 \
b101111000000 ^
b11000000 #
b11000000 2
b11000000 X
b11000000 b
b11111 *
b11111 D
b11111 ]
b11111 a
b1001011 =
b1001011 Y
1,
#350
0,
#355
bz Q
b1011 O
04
16
b0 C
b0 L
09
0:
1<
1W
b1000000001000 >
b1000000001000 U
b1000000001000 V
b1011 )
b1011 A
b1011 I
b1011 J
0$
1,
#360
0,
#365
17
0<
0W
b100000001000 >
b100000001000 U
b100000001000 V
b0 %
b0 3
b0 P
b1100 &
b1100 ;
b1100 T
1$
b101000 (
b101000 @
b101000 \
b101000 ^
b101000 #
b101000 2
b101000 X
b101000 b
b100000 *
b100000 D
b100000 ]
b100000 a
b11000000 =
b11000000 Y
1,
#370
0,
#375
07
1<
1W
b1000000001000 >
b1000000001000 U
b1000000001000 V
b1001110 (
b1001110 @
b1001110 \
b1001110 ^
b1001110 #
b1001110 2
b1001110 X
b1001110 b
b101000 *
b101000 D
b101000 ]
b101000 a
0$
1,
#380
0,
#385
b1110 G
b1110 H
b1110 M
b1110 N
b1110 Q
b1110 !
b1110 /
b1110 K
b1110 Z
b1110 _
bz O
14
06
b10 C
b10 L
19
1:
0<
0W
b11010000010 >
b11010000010 U
b11010000010 V
b1110 %
b1110 3
b1110 P
b100 &
b100 ;
b100 T
1$
b111001000100 (
b111001000100 @
b111001000100 \
b111001000100 ^
b1000100 #
b1000100 2
b1000100 X
b1000100 b
b101001 *
b101001 D
b101001 ]
b101001 a
b1001110 =
b1001110 Y
1,
#390
0,
#395
bz Q
b1110 O
04
16
b0 C
b0 L
09
0:
1<
1W
b1000000001000 >
b1000000001000 U
b1000000001000 V
b1110 )
b1110 A
b1110 I
b1110 J
0$
1,
#400
0,
#405
b100 G
b100 H
b100 M
b100 N
b100 Q
b100 !
b100 /
b100 K
b100 Z
b100 _
bz O
14
06
b10 C
b10 L
19
1:
0<
0W
b11010000010 >
b11010000010 U
b11010000010 V
b100 %
b100 3
b100 P
1$
b10001110011 (
b10001110011 @
b10001110011 \
b10001110011 ^
b1110011 #
b1110011 2
b1110011 X
b1110011 b
b101010 *
b101010 D
b101010 ]
b101010 a
b1000100 =
b1000100 Y
1,
#410
0,
#415
bz Q
b100 O
04
16
b0 C
b0 L
09
0:
1<
1W
b1000000001000 >
b1000000001000 U
b1000000001000 V
b100 )
b100 A
b100 I
b100 J
0$
1,
#420
0,
#425
11
1?
0W
b1000000111000 >
b1000000111000 U
b1000000111000 V
b11 %
b11 3
b11 P
b111 &
b111 ;
b111 T
1$
b1100110011 (
b1100110011 @
b1100110011 \
b1100110011 ^
b110011 #
b110011 2
b110011 X
b110011 b
b101011 *
b101011 D
b101011 ]
b101011 a
b1110011 =
b1110011 Y
1,
#430
0,
